azext_batch/__init__.py
azext_batch/_client_factory.py
azext_batch/_help.py
azext_batch/_params.py
azext_batch/_validators.py
azext_batch/azext_metadata.json
azext_batch/commands.py
azext_batch/custom.py
azext_batch/version.py
azure_batch_cli_extensions-7.0.0.dist-info/METADATA
azure_batch_cli_extensions-7.0.0.dist-info/WHEEL
azure_batch_cli_extensions-7.0.0.dist-info/top_level.txt
azure_batch_cli_extensions-7.0.0.dist-info/RECORD
