Metadata-Version: 2.1
Name: azure-batch-cli-extensions
Version: 7.0.0
Summary: Additional commands for working with Azure Batch service
Home-page: https://github.com/Azure/azure-batch-cli-extensions
Author: Microsoft Corporation
Author-email: azpycli@microsoft.com
License: MIT
Classifier: Development Status :: 4 - Beta
Classifier: Intended Audience :: Developers
Classifier: Intended Audience :: System Administrators
Classifier: Programming Language :: Python
Classifier: Programming Language :: Python :: 2
Classifier: Programming Language :: Python :: 2.7
Classifier: Programming Language :: Python :: 3
Classifier: Programming Language :: Python :: 3.4
Classifier: Programming Language :: Python :: 3.5
Classifier: Programming Language :: Python :: 3.6
Classifier: License :: OSI Approved :: MIT License
Requires-Dist: azure-batch-extensions (<9.1,>=9.0.0)
Requires-Dist: pycparser (==2.18)
